chemi
test
