Metadata-Version: 1.2
Name: cheminformatics
Version: 0.0.3
Summary: Data science and machine learning tools for chemistry applications
Home-page: https://github.com/jwgerlach00/cheminformatics
Author: Jacob Gerlach
Author-email: jwgerlach00@gmail.com
License: MIT
Platform: UNKNOWN
Requires-Python: >=3.6
